vocles/__init__.py
vocles/dataset.py
vocles/vocalization.py
vocles-0.1.0.dist-info/LICENSE
vocles-0.1.0.dist-info/WHEEL
vocles-0.1.0.dist-info/METADATA
vocles-0.1.0.dist-info/RECORD
